diskcache-stubs/__init__.pyi
diskcache-stubs/_typeshed.pyi
diskcache-stubs/cli.pyi
diskcache-stubs/core.pyi
diskcache-stubs/djangocache.pyi
diskcache-stubs/fanout.pyi
diskcache-stubs/persistent.pyi
diskcache-stubs/recipes.pyi
diskcache_stubs-5.6.3.5.20240619.dist-info/METADATA
diskcache_stubs-5.6.3.5.20240619.dist-info/WHEEL
diskcache_stubs-5.6.3.5.20240619.dist-info/licenses/LICENSE
diskcache_stubs-5.6.3.5.20240619.dist-info/RECORD
