Metadata-Version: 2.3
Name: diskcache-stubs
Version: 5.6.3.5.20240619
Summary: diskcache stubs
Project-URL: Repository, https://github.com/phi-friday/diskcache-stubs
Author-email: phi <phi.friday@gmail.com>
License:                                  Apache License
License-File: LICENSE
Classifier: Development Status :: 4 - Beta
Classifier: License :: OSI Approved :: Apache Software License
Classifier: Programming Language :: Python :: 3
Classifier: Programming Language :: Python :: Implementation :: CPython
Classifier: Typing :: Stubs Only
Requires-Python: >=3
Requires-Dist: typing-extensions>=4.4.0
